br_docs/__init__.py
br_docs/validators/__init__.py
br_docs/validators/cert.py
br_docs/validators/cnh.py
br_docs/validators/cnpj.py
br_docs/validators/cns.py
br_docs/validators/cpf.py
br_docs/validators/nis.py
br_docs/validators/renavam.py
br_docs/validators/sei.py
br_docs/validators/te.py
br_docs/validators/types/__init__.py
br_docs/validators/types/format.py
brdocs_validation-0.4.0.dist-info/LICENSE.txt
brdocs_validation-0.4.0.dist-info/METADATA
brdocs_validation-0.4.0.dist-info/WHEEL
brdocs_validation-0.4.0.dist-info/top_level.txt
brdocs_validation-0.4.0.dist-info/RECORD
