Metadata-Version: 2.1
Name: brdocs-validation
Version: 0.4.0
Summary: Validate brazilian documents using Type Hints in classes inheriting Pydantic's (V2) BaseModel
Author-email: Vinícius Aguiar <vaguiararqdevsoftware@proton.me>
Maintainer-email: Vinícius Aguiar <vaguiararqdevsoftware@proton.me>
Project-URL: Repository, https://github.com/vinicius-oa/BRdocs-validation
Keywords: pydantic-v2,cpf-validador,cnpj-validador,validador-pispasep,validador-titulo-eleitor
Classifier: Development Status :: 5 - Production/Stable
Classifier: Framework :: Pydantic :: 2
Classifier: Intended Audience :: Developers
Classifier: Topic :: Software Development :: Build Tools
Classifier: License :: OSI Approved :: MIT License
Classifier: Natural Language :: English
Classifier: Programming Language :: Python :: 3.10
Classifier: Programming Language :: Python :: 3.11
Classifier: Programming Language :: Python :: 3.12
Classifier: Programming Language :: Python :: Implementation :: CPython
Classifier: Topic :: Software Development :: Libraries :: Python Modules
Requires-Python: >=3.10
License-File: LICENSE.txt
Requires-Dist: pydantic >=2.0
Provides-Extra: dev
Requires-Dist: build ; extra == 'dev'
Requires-Dist: mypy ; extra == 'dev'
Requires-Dist: pytest ; extra == 'dev'
Requires-Dist: wheel ; extra == 'dev'
Requires-Dist: twine ; extra == 'dev'
Requires-Dist: tox ; extra == 'dev'
Requires-Dist: ruff ; extra == 'dev'
